veilcord/__init__.py
veilcord/__main__.py
veilcord/__session__.py
veilcord/__solver__.py
veilcord/__udcord__.py
veilcord/models/device.py
veilcord/models/dynamic.py
veilcord/models/websocket.py
veilcord-0.0.7.5.dist-info/LICENSE
veilcord-0.0.7.5.dist-info/METADATA
veilcord-0.0.7.5.dist-info/WHEEL
veilcord-0.0.7.5.dist-info/top_level.txt
veilcord-0.0.7.5.dist-info/RECORD
